findex-6.0.2.dist-info/METADATA
findex-6.0.2.dist-info/WHEEL
findex-6.0.2.dist-info/license_files/LICENSE.md
cloudproof_findex/__init__.py
cloudproof_findex/__init__.pyi
cloudproof_findex/py.typed
cloudproof_findex/cloudproof_findex.pyd
findex-6.0.2.dist-info/RECORD
