Metadata-Version: 2.3
Name: findex
Version: 6.0.2
Classifier: Programming Language :: Rust
Classifier: Programming Language :: Python :: Implementation :: CPython
Classifier: Programming Language :: Python :: Implementation :: PyPy
Requires-Dist: cffi
License-File: LICENSE.md
Summary: Cosmian Cloudproof Findex library
Author: Théophile Brézot<theophile.brezot@cosmian.com>, Emmanuel Coste<emmanuel.coste@cosmian.com>, Thibaud Dauce<thibaud.dauce@cosmian.com>, Bruno Grieder<bruno.grieder@cosmian.com>, Hugo Rosenkranz-costa<hugo.rosenkranz@cosmian.com>
Author-email: Théophile Brézot<theophile.brezot@cosmian.com>, Emmanuel Coste<emmanuel.coste@cosmian.com>, Thibaud Dauce<thibaud.dauce@cosmian.com>, Bruno Grieder<bruno.grieder@cosmian.com>, Hugo Rosenkranz-costa<hugo.rosenkranz@cosmian.com>
Requires-Python: >=3.7
Project-URL: Source Code, https://github.com/cosmian/cloudproof_rust/
